neurodiffeq/__init__.py
neurodiffeq/_version_utils.py
neurodiffeq/callbacks.py
neurodiffeq/conditions.py
neurodiffeq/function_basis.py
neurodiffeq/generator.py
neurodiffeq/generators.py
neurodiffeq/losses.py
neurodiffeq/monitors.py
neurodiffeq/networks.py
neurodiffeq/neurodiffeq.py
neurodiffeq/ode.py
neurodiffeq/operators.py
neurodiffeq/pde.py
neurodiffeq/pde_spherical.py
neurodiffeq/solvers.py
neurodiffeq/solvers_utils.py
neurodiffeq/temporal.py
neurodiffeq/utils.py
neurodiffeq/hypersolver/__init__.py
neurodiffeq/hypersolver/hypersolver.py
neurodiffeq/hypersolver/numerical_solvers.py
tests/__init__.py
tests/test_callbacks.py
tests/test_conditions.py
tests/test_function_basis.py
tests/test_generators.py
tests/test_hypersolver.py
tests/test_losses.py
tests/test_monitors.py
tests/test_networks.py
tests/test_neurodiffeq.py
tests/test_numerical_solver.py
tests/test_ode.py
tests/test_operators_cartesian.py
tests/test_operators_cylindrical.py
tests/test_operators_identities.py
tests/test_operators_spherical.py
tests/test_pde.py
tests/test_pde_spherical.py
tests/test_solvers.py
tests/test_solvers_utils.py
tests/test_temporal.py
neurodiffeq-0.5.1.dist-info/LICENSE
neurodiffeq-0.5.1.dist-info/METADATA
neurodiffeq-0.5.1.dist-info/WHEEL
neurodiffeq-0.5.1.dist-info/top_level.txt
neurodiffeq-0.5.1.dist-info/RECORD
