Metadata-Version: 2.1
Name: neurodiffeq
Version: 0.5.1
Summary: A light-weight & flexible library for solving differential equations using neural networks based on PyTorch. 
Home-page: https://github.com/NeuroDiffGym/neurodiffeq
Author: neurodiffgym
Author-email: shuheng_liu@g.harvard.edu
License: UNKNOWN
Download-URL: https://github.com/NeuroDiffGym/neurodiffeq/archive/v0.5.1.tar.gz
Keywords: neural network,deep learning,differential equation,ODE,PDE,spectral method,numerical method,pytorch
Platform: UNKNOWN
Classifier: Programming Language :: Python :: 3
Classifier: License :: OSI Approved :: MIT License
Classifier: Operating System :: OS Independent
Requires-Python: >=3.6
Requires-Dist: wheel
Requires-Dist: packaging
Requires-Dist: matplotlib
Requires-Dist: numpy
Requires-Dist: torch
Requires-Dist: scipy
Requires-Dist: pytest
Requires-Dist: pandas
Requires-Dist: seaborn
Requires-Dist: dill
Requires-Dist: tensorboard
Requires-Dist: tqdm
Requires-Dist: requests
